MANIFEST.in
setup.cfg
setup.py
datahub/__init__.py
datahub.gov.dot.nhtsa.recall.egg-info/PKG-INFO
datahub.gov.dot.nhtsa.recall.egg-info/SOURCES.txt
datahub.gov.dot.nhtsa.recall.egg-info/dependency_links.txt
datahub.gov.dot.nhtsa.recall.egg-info/entry_points.txt
datahub.gov.dot.nhtsa.recall.egg-info/not-zip-safe
datahub.gov.dot.nhtsa.recall.egg-info/paster_plugins.txt
datahub.gov.dot.nhtsa.recall.egg-info/top_level.txt
datahub/gov/dot/nhtsa/recall/README.txt
datahub/gov/dot/nhtsa/recall/__init__.py
datahub/gov/dot/nhtsa/recall/process.sh
datahub/gov/dot/nhtsa/recall/crawl/Readme.txt
datahub/gov/dot/nhtsa/recall/crawl/__init__.py
datahub/gov/dot/nhtsa/recall/crawl/crawl.sh
datahub/gov/dot/nhtsa/recall/crawl/download.sh
datahub/gov/dot/nhtsa/recall/crawl/download_list.txt
datahub/gov/dot/nhtsa/recall/crawl/harvestman-datahubgovdotnhtsarecall.xml
datahub/gov/dot/nhtsa/recall/hdf5/READEM_hdf5.txt
datahub/gov/dot/nhtsa/recall/hdf5/__init__.py
datahub/gov/dot/nhtsa/recall/load/__init__.py
datahub/gov/dot/nhtsa/recall/load/load.py
datahub/gov/dot/nhtsa/recall/load/load.sh
datahub/gov/dot/nhtsa/recall/load/model.py
datahub/gov/dot/nhtsa/recall/load/recall.py
datahub/gov/dot/nhtsa/recall/parse/__init__.py
datahub/gov/dot/nhtsa/recall/parse/parse.sh
datahub/gov/dot/nhtsa/recall/web/__init__.py