Metadata-Version: 1.0
Name: datahub.gov.dot.nhtsa.recall
Version: 0.2dev
Summary: Recall Database from nhtsa
Home-page: http://www.lucasmanual.com/mywiki/DataHub
Author: Lukasz Szybalski
Author-email: szybalski@gmail.com
License: GPL
Keywords: nhtsa datahub gov dot dot recall
Platform: UNKNOWN
